swarmauri_keyprovider_remote_jwks/RemoteJwksKeyProvider.py
swarmauri_keyprovider_remote_jwks/__init__.py
swarmauri_keyprovider_remote_jwks-0.2.0.dev5.dist-info/LICENSE
swarmauri_keyprovider_remote_jwks-0.2.0.dev5.dist-info/METADATA
swarmauri_keyprovider_remote_jwks-0.2.0.dev5.dist-info/WHEEL
swarmauri_keyprovider_remote_jwks-0.2.0.dev5.dist-info/entry_points.txt
swarmauri_keyprovider_remote_jwks-0.2.0.dev5.dist-info/RECORD
